omnimd_appledev_reader/__init__.py
omnimd_appledev_reader/reader.py
omnimd_appledev_reader-0.1.0.dist-info/METADATA
omnimd_appledev_reader-0.1.0.dist-info/WHEEL
omnimd_appledev_reader-0.1.0.dist-info/entry_points.txt
omnimd_appledev_reader-0.1.0.dist-info/RECORD
